pygremlinbox_eupl_1_1/__init__.py
pygremlinbox_eupl_1_1-1.4.0.dist-info/licenses/LICENCE
pygremlinbox_eupl_1_1-1.4.0.dist-info/METADATA
pygremlinbox_eupl_1_1-1.4.0.dist-info/WHEEL
pygremlinbox_eupl_1_1-1.4.0.dist-info/top_level.txt
pygremlinbox_eupl_1_1-1.4.0.dist-info/RECORD
